python_yaml_config/__init__.py
python_yaml_config/app_config.py
python_yaml_config/utils/__init__.py
python_yaml_config/utils/convert.py
python_yaml_config-1.0.0.dist-info/LICENSE
python_yaml_config-1.0.0.dist-info/METADATA
python_yaml_config-1.0.0.dist-info/WHEEL
python_yaml_config-1.0.0.dist-info/RECORD
